setup.py
Tictactoe_Meh/Board_org.py
Tictactoe_Meh/Play.py
Tictactoe_Meh/__init__.py
Tictactoe_Meh.egg-info/PKG-INFO
Tictactoe_Meh.egg-info/SOURCES.txt
Tictactoe_Meh.egg-info/dependency_links.txt
Tictactoe_Meh.egg-info/not-zip-safe
Tictactoe_Meh.egg-info/top_level.txt