Metadata-Version: 1.0
Name: Tictactoe-Meh
Version: 0.2
Summary: Playing Tic Toc Toe Game between two Players
Home-page: UNKNOWN
Author: UNKNOWN
Author-email: UNKNOWN
License: UNKNOWN
Platform: UNKNOWN
